LICENSE.txt
MANIFEST.in
setup.py
convert_php/__init__.py
convert_php/convert_php.py
diablo_python.egg-info/PKG-INFO
diablo_python.egg-info/SOURCES.txt
diablo_python.egg-info/dependency_links.txt
diablo_python.egg-info/not-zip-safe
diablo_python.egg-info/requires.txt
diablo_python.egg-info/top_level.txt
file_parsing/__init__.py
file_parsing/file_parsing.py
simple_math/__init__.py
simple_math/simple_math.py
tests/__init__.py
tests/convert_php_test.py
tests/file_parsing_test.py
tests/simple_math_test.py
tests/test_hours_data/file1.vim
tests/test_hours_data/file2.vim
tests/test_hours_data/file3.vim
tests/test_hours_data/file4.vim
tests/test_hours_data/file5.txt