Metadata-Version: 1.0
Name: diablo-python
Version: 0.0.2
Summary: Simple libraries and repurposable code for inclusion in projects and general use.
Home-page: https://github.com/bbusenius/Diablo-Python
Author: Brad Busenius
Author-email: bbusenius@gmail.com
License: GNU GPLv3, see LICENSE.txt
Platform: UNKNOWN
